simple_imaging/__init__.py
simple_imaging/errors.py
simple_imaging/image.py
simple_imaging/matrix.py
simple_imaging/types.py
simple_imaging/utils.py
simple_imaging-0.8.3.dist-info/LICENSE
simple_imaging-0.8.3.dist-info/METADATA
simple_imaging-0.8.3.dist-info/WHEEL
simple_imaging-0.8.3.dist-info/top_level.txt
simple_imaging-0.8.3.dist-info/RECORD
