Metadata-Version: 2.1
Name: simple-imaging
Version: 0.8.3
Summary: a simple digital image processing library
Home-page: https://github.com/deadpyxel/simple_imaging
Author: deadpyxel
Author-email: ghost0092@gmail.com
License: MIT
Platform: UNKNOWN
Classifier: Development Status :: 3 - Alpha
Classifier: License :: OSI Approved :: MIT License
Classifier: Programming Language :: Python :: 3
Classifier: Programming Language :: Python :: 3 :: Only
Classifier: Programming Language :: Python :: 3.7
Classifier: Programming Language :: Python :: 3.8
Classifier: Programming Language :: Python :: 3.9
Classifier: Programming Language :: Python :: Implementation :: CPython
Requires-Python: >=3.7
